greenflash/__init__.py
greenflash/_base_client.py
greenflash/_client.py
greenflash/_compat.py
greenflash/_constants.py
greenflash/_exceptions.py
greenflash/_files.py
greenflash/_models.py
greenflash/_qs.py
greenflash/_resource.py
greenflash/_response.py
greenflash/_streaming.py
greenflash/_types.py
greenflash/_version.py
greenflash/py.typed
greenflash/_utils/__init__.py
greenflash/_utils/_compat.py
greenflash/_utils/_datetime_parse.py
greenflash/_utils/_json.py
greenflash/_utils/_logs.py
greenflash/_utils/_proxy.py
greenflash/_utils/_reflection.py
greenflash/_utils/_resources_proxy.py
greenflash/_utils/_streams.py
greenflash/_utils/_sync.py
greenflash/_utils/_transform.py
greenflash/_utils/_typing.py
greenflash/_utils/_utils.py
greenflash/lib/.keep
greenflash/resources/__init__.py
greenflash/resources/events.py
greenflash/resources/interactions.py
greenflash/resources/messages.py
greenflash/resources/organizations.py
greenflash/resources/prompts.py
greenflash/resources/ratings.py
greenflash/resources/users.py
greenflash/types/__init__.py
greenflash/types/component_input_param.py
greenflash/types/component_update_param.py
greenflash/types/create_event_response.py
greenflash/types/create_message_response.py
greenflash/types/create_organization_response.py
greenflash/types/create_prompt_response.py
greenflash/types/create_user_response.py
greenflash/types/delete_prompt_response.py
greenflash/types/event_create_params.py
greenflash/types/get_interaction_analytics_response.py
greenflash/types/get_organization_analytics_response.py
greenflash/types/get_prompt_response.py
greenflash/types/get_user_analytics_response.py
greenflash/types/interaction_get_interaction_analytics_params.py
greenflash/types/interaction_list_params.py
greenflash/types/list_interactions_response.py
greenflash/types/list_organizations_response.py
greenflash/types/list_prompts_response.py
greenflash/types/list_users_response.py
greenflash/types/log_rating_response.py
greenflash-1.1.0.dist-info/METADATA
greenflash-1.1.0.dist-info/WHEEL
greenflash-1.1.0.dist-info/licenses/LICENSE
greenflash-1.1.0.dist-info/RECORD
